{"ongoing_trials": {"tuner0": "0001"}, "hyperparameters": {"space": [{"class_name": "Int", "config": {"name": "start_filters", "default": null, "conditions": [], "min_value": 10, "max_value": 20, "step": 1, "sampling": "linear"}}, {"class_name": "Float", "config": {"name": "dropout_rate", "default": 0.1, "conditions": [], "min_value": 0.1, "max_value": 0.25, "step": 0.03, "sampling": "linear"}}, {"class_name": "Float", "config": {"name": "learning_rate", "default": 0.01, "conditions": [], "min_value": 0.01, "max_value": 0.3, "step": 0.01, "sampling": "linear"}}, {"class_name": "Choice", "config": {"name": "kernel_size", "default": 3, "conditions": [], "values": [3, 5, 7], "ordered": true}}, {"class_name": "Choice", "config": {"name": "activation", "default": "relu", "conditions": [], "values": ["relu", "leaky_relu", "elu"], "ordered": false}}, {"class_name": "Choice", "config": {"name": "optimizer", "default": "adam", "conditions": [], "values": ["adam", "rmsprop", "sgd"], "ordered": false}}, {"class_name": "Choice", "config": {"name": "loss", "default": "binary_crossentropy", "conditions": [], "values": ["binary_crossentropy", "mean_squared_error"], "ordered": false}}], "values": {"start_filters": 10, "dropout_rate": 0.1, "learning_rate": 0.01, "kernel_size": 3, "activation": "relu", "optimizer": "adam", "loss": "binary_crossentropy"}}, "start_order": ["0000", "0001"], "end_order": ["0000"], "run_times": {"0000": 1}, "retry_queue": [], "seed": 9998, "seed_state": 10012, "tried_so_far": ["691365c0668df1eb8dded7843eee926c", "3acd0643f99ccb73cacf5385a764e859"], "id_to_hash": {"0000": "3acd0643f99ccb73cacf5385a764e859", "0001": "691365c0668df1eb8dded7843eee926c"}, "display": {"search_start": "2023-12-20T18:19:42.612432", "trial_start": {"0000": "2023-12-20T18:19:42.612432"}, "trial_number": {"0000": 1}}, "hyperband_iterations": 1, "max_epochs": 10, "min_epochs": 1, "factor": 3, "brackets": [{"bracket_num": 2, "rounds": [[{"past_id": null, "id": "0000"}, {"past_id": null, "id": "0001"}], [], []]}], "current_bracket": 2, "current_iteration": 0}